LICENSE
cvraft/__init__.py
cvraft/cli.py
cvraft/extension.py
cvraft/templates/cv.html
cvraft-0.1.4.dist-info/entry_points.txt
cvraft-0.1.4.dist-info/LICENSE
cvraft-0.1.4.dist-info/WHEEL
cvraft-0.1.4.dist-info/METADATA
cvraft-0.1.4.dist-info/RECORD
