Metadata-Version: 2.1
Name: cvraft
Version: 0.1.4
Summary: Build your CV written in Markdown
Home-page: https://github.com/cvraft/cvraft
License: MIT
Author: Manh-Ha VU
Author-email: dev@manhhavu.com
Requires-Python: >=3.10,<4.0
Classifier: License :: OSI Approved :: MIT License
Classifier: Programming Language :: Python :: 3
Classifier: Programming Language :: Python :: 3.10
Requires-Dist: Jinja2 (>=3.0.3,<4.0.0)
Requires-Dist: Markdown (>=3.3.6,<4.0.0)
Requires-Dist: beautifulsoup4 (>=4.10.0,<5.0.0)
Requires-Dist: python-frontmatter (>=1.0.0,<2.0.0)
Requires-Dist: typer (>=0.4.0,<0.5.0)
Project-URL: Repository, https://github.com/cvraft/cvraft
